pelfy/__init__.py
pelfy/_fields_data.py
pelfy/_main.py
pelfy/_output_formatter.py
pelfy/py.typed
pelfy-1.0.5.dist-info/licenses/LICENSE
pelfy-1.0.5.dist-info/METADATA
pelfy-1.0.5.dist-info/WHEEL
pelfy-1.0.5.dist-info/top_level.txt
pelfy-1.0.5.dist-info/RECORD
